anbefm/__init__.py
anbefm/app.py
anbefm/bc_exceptions.py
anbefm/handle_payload.py
anbefm/handle_upload_file.py
anbefm/jwt.py
anbefm/manage.py
anbefm/validator.py
anbefm/base/__init__.py
anbefm/base/log.py
anbefm/base/utils.py
anbefm/model/__init__.py
anbefm/model/m_base.py
anbefm/model/m_dao.py
anbefm-0.0.5.dist-info/METADATA
anbefm-0.0.5.dist-info/WHEEL
anbefm-0.0.5.dist-info/top_level.txt
anbefm-0.0.5.dist-info/RECORD
