Metadata-Version: 2.4
Name: anbefm
Version: 0.0.5
Summary: 一个后端框架
Home-page: https://gitee.com/liubei90/basic.git
Author: liubei
Author-email: 1021086660@qq.com
Classifier: Programming Language :: Python :: 3
Classifier: License :: OSI Approved :: MIT License
Classifier: Operating System :: OS Independent
Requires-Python: >=3.6
Requires-Dist: aiomysql==0.0.21
Requires-Dist: tornado==6.1
Requires-Dist: click==7.1.2
Requires-Dist: PyMySQL==0.9.3
Dynamic: author
Dynamic: author-email
Dynamic: classifier
Dynamic: description
Dynamic: description-content-type
Dynamic: home-page
Dynamic: requires-dist
Dynamic: requires-python
Dynamic: summary
